nicegui_command_palette/__init__.py
nicegui_command_palette/command_palette.py
nicegui_command_palette/command_table.vue
nicegui_command_palette-0.3.2.dist-info/LICENSE
nicegui_command_palette-0.3.2.dist-info/METADATA
nicegui_command_palette-0.3.2.dist-info/WHEEL
nicegui_command_palette-0.3.2.dist-info/top_level.txt
nicegui_command_palette-0.3.2.dist-info/RECORD
