Metadata-Version: 2.1
Name: nicegui-command-palette
Version: 0.3.2
Summary: A command palette for NiceGUI applications
Author-email: David Kincaid <daelonsuzuka@gmail.com>
License: MIT License
Project-URL: Homepage, https://github.com/DaelonSuzuka/nicegui-command-palette
Project-URL: Repository, https://github.com/DaelonSuzuka/nicegui-command-palette
Project-URL: Issues, https://github.com/DaelonSuzuka/nicegui-command-palette/issues
Classifier: Development Status :: 4 - Beta
Classifier: Intended Audience :: Developers
Classifier: Topic :: Software Development :: Widget Sets
Classifier: Operating System :: OS Independent
Classifier: License :: OSI Approved :: MIT License
Classifier: Programming Language :: Python :: 3
Classifier: Programming Language :: Python :: 3.11
Classifier: Programming Language :: Python :: 3.12
Classifier: Programming Language :: Python :: 3.13
Requires-Python: >=3.12
License-File: LICENSE
Requires-Dist: nicegui
